eigen_analysis/__init__.py
eigen_analysis/base.py
eigen_analysis/eca.py
eigen_analysis/ueca.py
eigen_analysis/utils.py
eigen_analysis/version.py
eigen_analysis/visualization.py
eigen_analysis-0.1.6.dist-info/METADATA
eigen_analysis-0.1.6.dist-info/WHEEL
eigen_analysis-0.1.6.dist-info/top_level.txt
eigen_analysis-0.1.6.dist-info/RECORD
