Metadata-Version: 2.4
Name: eigen-analysis
Version: 0.1.6
Summary: Eigen-Component Analysis for classification and clustering
Home-page: https://github.com/lachlanchen/eca
Author: Lachlan Chen
Author-email: lach@lazyingoronlyideas.art
Classifier: Programming Language :: Python :: 3
Classifier: License :: OSI Approved :: MIT License
Classifier: Operating System :: OS Independent
Classifier: Intended Audience :: Science/Research
Classifier: Topic :: Scientific/Engineering :: Artificial Intelligence
Requires-Python: >=3.7
Requires-Dist: numpy>=1.18.0
Requires-Dist: torch>=1.7.0
Requires-Dist: matplotlib>=3.3.0
Requires-Dist: seaborn>=0.11.0
Requires-Dist: scikit-learn>=0.24.0
Requires-Dist: scipy>=1.6.0
Dynamic: author
Dynamic: author-email
Dynamic: classifier
Dynamic: description
Dynamic: description-content-type
Dynamic: home-page
Dynamic: requires-dist
Dynamic: requires-python
Dynamic: summary
